bonecommand/__init__.py
bonecommand/__main__.py
bonecommand/basic/3rd.py
bonecommand/basic/__init__.py
bonecommand/basic/__main__.py
bonecommand/bone-command.zsh
bonecommand/build.py
bonecommand/command.py
bonecommand/docker.py
bonecommand/git/__init__.py
bonecommand/git/__main__.py
bonecommand/git/utils.py
bonecommand/gui.py
bonecommand/pdf/0.pdf
bonecommand/pdf/1.pdf
bonecommand/pdf/2.pdf
bonecommand/pdf/__init__.py
bonecommand/pdf/__main__.py
bonecommand/pdf/main.pdf
bonecommand/pdf/utils.py
bonecommand/ssh/__init__.py
bonecommand/ssh/__main__.py
bonecommand/ssh/ssh.py
bonecommand/ssh/utils.py
bonecommand/utils.py
bonetools/__init__.py
bonetools/demo.py
bonetools/trigger.py
BoneCommand-0.0.1.dist-info/WHEEL
BoneCommand-0.0.1.dist-info/METADATA
BoneCommand-0.0.1.dist-info/RECORD
