Metadata-Version: 2.1
Name: BoneCommand
Version: 0.0.1
Summary: 一个用于提升效率的命令行工具
License: MIT
Author-email: Rongrui Zhan <2742392377@qq.com>
Requires-Python: >=3.7
Requires-Dist: psutil
Requires-Dist: pydantic
Requires-Dist: pypdf
Requires-Dist: pyperclip
Requires-Dist: rich
Requires-Dist: typer
